colcon_bazel/__init__.py
colcon_bazel/argcomplete_completer/__init__.py
colcon_bazel/argcomplete_completer/bazel_args.py
colcon_bazel/environment/__init__.py
colcon_bazel/package_identification/__init__.py
colcon_bazel/package_identification/bazel.py
colcon_bazel/task/__init__.py
colcon_bazel/task/bazel/__init__.py
colcon_bazel/task/bazel/build.py
colcon_bazel/task/bazel/test.py
colcon_bazel-0.1.0.dist-info/METADATA
colcon_bazel-0.1.0.dist-info/RECORD
colcon_bazel-0.1.0.dist-info/WHEEL
colcon_bazel-0.1.0.dist-info/entry_points.txt
colcon_bazel-0.1.0.dist-info/top_level.txt
colcon_bazel-0.1.0.dist-info/zip-safe
