Metadata-Version: 2.1
Name: colcon-bazel
Version: 0.1.0
Summary: Extension for colcon to support Bazel packages.
Home-page: https://colcon.readthedocs.io
Author: Mickael Gaillard
Author-email: mick.gaillard@gmail.com
Maintainer: Mickael Gaillard
Maintainer-email: mick.gaillard@gmail.com
License: Apache License, Version 2.0
Project-URL: GitHub, https://github.com/colcon/colcon-bazel/
Project-URL: Changelog, https://github.com/colcon/colcon-bazel/milestones?state=closed
Keywords: colcon
Platform: UNKNOWN
Classifier: Development Status :: 3 - Alpha
Classifier: Environment :: Plugins
Classifier: Intended Audience :: Developers
Classifier: License :: OSI Approved :: Apache Software License
Classifier: Operating System :: MacOS
Classifier: Operating System :: Microsoft :: Windows
Classifier: Operating System :: POSIX
Classifier: Programming Language :: Python
Classifier: Topic :: Software Development :: Build Tools
Requires-Dist: colcon-core (>=0.3.9)
Requires-Dist: colcon-library-path
Requires-Dist: pyparsing
